{
  "components": {
    "schemas": {
      "AcceptedAction": {
        "description": "One accepted Balancing Mechanism action (BOALF); level_from \u2192 level_to is the ramp.",
        "properties": {
          "acceptance_time": {
            "format": "date-time",
            "title": "Acceptance Time",
            "type": "string"
          },
          "bm_unit": {
            "anyOf": [
              {
                "type": "string"
              },
              {
                "type": "null"
              }
            ],
            "title": "Bm Unit"
          },
          "fuel_type": {
            "anyOf": [
              {
                "type": "string"
              },
              {
                "type": "null"
              }
            ],
            "title": "Fuel Type"
          },
          "level_from": {
            "title": "Level From",
            "type": "number"
          },
          "level_to": {
            "title": "Level To",
            "type": "number"
          },
          "national_grid_bm_unit": {
            "title": "National Grid Bm Unit",
            "type": "string"
          },
          "so_flag": {
            "title": "So Flag",
            "type": "boolean"
          },
          "unit_name": {
            "anyOf": [
              {
                "type": "string"
              },
              {
                "type": "null"
              }
            ],
            "title": "Unit Name"
          }
        },
        "required": [
          "national_grid_bm_unit",
          "bm_unit",
          "unit_name",
          "fuel_type",
          "acceptance_time",
          "level_from",
          "level_to",
          "so_flag"
        ],
        "title": "AcceptedAction",
        "type": "object"
      },
      "BatteryContext": {
        "description": "Supporting stats for the Battery Lab explainer tab.",
        "properties": {
          "avg_export_p_kwh": {
            "title": "Avg Export P Kwh",
            "type": "number"
          },
          "avg_import_p_kwh": {
            "title": "Avg Import P Kwh",
            "type": "number"
          },
          "avg_solar_cf": {
            "anyOf": [
              {
                "type": "number"
              },
              {
                "type": "null"
              }
            ],
            "title": "Avg Solar Cf"
          },
          "days": {
            "title": "Days",
            "type": "integer"
          },
          "demand_profile": {
            "items": {
              "$ref": "#/components/schemas/DemandBucket"
            },
            "title": "Demand Profile",
            "type": "array"
          },
          "export_tariff": {
            "title": "Export Tariff",
            "type": "string"
          },
          "green_overlap_pct": {
            "anyOf": [
              {
                "type": "number"
              },
              {
                "type": "null"
              }
            ],
            "title": "Green Overlap Pct"
          },
          "import_tariff": {
            "title": "Import Tariff",
            "type": "string"
          },
          "intraday": {
            "items": {
              "$ref": "#/components/schemas/PriceCarbonBucket"
            },
            "title": "Intraday",
            "type": "array"
          },
          "periods": {
            "title": "Periods",
            "type": "integer"
          },
          "presets": {
            "items": {
              "$ref": "#/components/schemas/BatterySpec"
            },
            "title": "Presets",
            "type": "array"
          },
          "region": {
            "title": "Region",
            "type": "string"
          },
          "tdcv_kwh": {
            "title": "Tdcv Kwh",
            "type": "integer"
          },
          "window_from": {
            "format": "date",
            "title": "Window From",
            "type": "string"
          },
          "window_to": {
            "format": "date",
            "title": "Window To",
            "type": "string"
          }
        },
        "required": [
          "window_from",
          "window_to",
          "days",
          "periods",
          "tdcv_kwh",
          "import_tariff",
          "export_tariff",
          "region",
          "avg_import_p_kwh",
          "avg_export_p_kwh",
          "avg_solar_cf",
          "green_overlap_pct",
          "presets",
          "intraday",
          "demand_profile"
        ],
        "title": "BatteryContext",
        "type": "object"
      },
      "BatterySimulation": {
        "description": "All strategy runs for one battery preset, plus shared context.",
        "properties": {
          "baseline_cost_gbp_year": {
            "title": "Baseline Cost Gbp Year",
            "type": "number"
          },
          "battery": {
            "$ref": "#/components/schemas/BatterySpec"
          },
          "days": {
            "title": "Days",
            "type": "integer"
          },
          "household_kwh": {
            "title": "Household Kwh",
            "type": "integer"
          },
          "periods": {
            "title": "Periods",
            "type": "integer"
          },
          "runs": {
            "items": {
              "$ref": "#/components/schemas/StrategyRun"
            },
            "title": "Runs",
            "type": "array"
          },
          "solar_generation_kwh_year": {
            "title": "Solar Generation Kwh Year",
            "type": "number"
          },
          "solar_kwp": {
            "title": "Solar Kwp",
            "type": "number"
          },
          "window_from": {
            "format": "date",
            "title": "Window From",
            "type": "string"
          },
          "window_to": {
            "format": "date",
            "title": "Window To",
            "type": "string"
          }
        },
        "required": [
          "battery",
          "household_kwh",
          "solar_kwp",
          "solar_generation_kwh_year",
          "window_from",
          "window_to",
          "days",
          "periods",
          "baseline_cost_gbp_year",
          "runs"
        ],
        "title": "BatterySimulation",
        "type": "object"
      },
      "BatterySpec": {
        "description": "A battery preset with an indicative installed cost (0% VAT, 2026 market).",
        "properties": {
          "capacity_kwh": {
            "title": "Capacity Kwh",
            "type": "number"
          },
          "cost_gbp": {
            "title": "Cost Gbp",
            "type": "number"
          },
          "key": {
            "title": "Key",
            "type": "string"
          },
          "name": {
            "title": "Name",
            "type": "string"
          },
          "power_kw": {
            "title": "Power Kw",
            "type": "number"
          },
          "round_trip_efficiency": {
            "title": "Round Trip Efficiency",
            "type": "number"
          }
        },
        "required": [
          "key",
          "name",
          "capacity_kwh",
          "power_kw",
          "round_trip_efficiency",
          "cost_gbp"
        ],
        "title": "BatterySpec",
        "type": "object"
      },
      "BidStack": {
        "description": "The balancing-mechanism offer stack for the latest settlement period, cheapest first.",
        "properties": {
          "entries": {
            "items": {
              "$ref": "#/components/schemas/BidStackEntry"
            },
            "title": "Entries",
            "type": "array"
          },
          "settlement_period": {
            "anyOf": [
              {
                "type": "integer"
              },
              {
                "type": "null"
              }
            ],
            "title": "Settlement Period"
          }
        },
        "required": [
          "settlement_period",
          "entries"
        ],
        "title": "BidStack",
        "type": "object"
      },
      "BidStackEntry": {
        "properties": {
          "accepted": {
            "title": "Accepted",
            "type": "boolean"
          },
          "national_grid_bm_unit": {
            "title": "National Grid Bm Unit",
            "type": "string"
          },
          "offer_price": {
            "title": "Offer Price",
            "type": "number"
          },
          "volume_mw": {
            "title": "Volume Mw",
            "type": "number"
          }
        },
        "required": [
          "national_grid_bm_unit",
          "offer_price",
          "volume_mw",
          "accepted"
        ],
        "title": "BidStackEntry",
        "type": "object"
      },
      "Carbon": {
        "properties": {
          "from_ts": {
            "format": "date-time",
            "title": "From Ts",
            "type": "string"
          },
          "intensity_gco2": {
            "anyOf": [
              {
                "type": "integer"
              },
              {
                "type": "null"
              }
            ],
            "title": "Intensity Gco2"
          },
          "intensity_index": {
            "title": "Intensity Index",
            "type": "string"
          }
        },
        "required": [
          "from_ts",
          "intensity_gco2",
          "intensity_index"
        ],
        "title": "Carbon",
        "type": "object"
      },
      "CarbonPoint": {
        "properties": {
          "actual_gco2": {
            "anyOf": [
              {
                "type": "integer"
              },
              {
                "type": "null"
              }
            ],
            "title": "Actual Gco2"
          },
          "forecast_gco2": {
            "anyOf": [
              {
                "type": "integer"
              },
              {
                "type": "null"
              }
            ],
            "title": "Forecast Gco2"
          },
          "from_ts": {
            "format": "date-time",
            "title": "From Ts",
            "type": "string"
          },
          "intensity_gco2": {
            "anyOf": [
              {
                "type": "integer"
              },
              {
                "type": "null"
              }
            ],
            "title": "Intensity Gco2"
          },
          "intensity_index": {
            "title": "Intensity Index",
            "type": "string"
          }
        },
        "required": [
          "from_ts",
          "forecast_gco2",
          "actual_gco2",
          "intensity_gco2",
          "intensity_index"
        ],
        "title": "CarbonPoint",
        "type": "object"
      },
      "DemandBucket": {
        "description": "Typical household demand in one settlement period (TDCV-scaled Elexon PC1).",
        "properties": {
          "avg_kwh": {
            "title": "Avg Kwh",
            "type": "number"
          },
          "settlement_period": {
            "title": "Settlement Period",
            "type": "integer"
          },
          "summer_weekday_kwh": {
            "title": "Summer Weekday Kwh",
            "type": "number"
          },
          "winter_weekday_kwh": {
            "title": "Winter Weekday Kwh",
            "type": "number"
          }
        },
        "required": [
          "settlement_period",
          "avg_kwh",
          "winter_weekday_kwh",
          "summer_weekday_kwh"
        ],
        "title": "DemandBucket",
        "type": "object"
      },
      "DispatchBucket": {
        "description": "The battery's average behaviour in one settlement period across the window.",
        "properties": {
          "charge_kwh": {
            "title": "Charge Kwh",
            "type": "number"
          },
          "charge_solar_kwh": {
            "title": "Charge Solar Kwh",
            "type": "number"
          },
          "discharge_kwh": {
            "title": "Discharge Kwh",
            "type": "number"
          },
          "export_p_kwh": {
            "title": "Export P Kwh",
            "type": "number"
          },
          "import_p_kwh": {
            "title": "Import P Kwh",
            "type": "number"
          },
          "intensity_gco2": {
            "anyOf": [
              {
                "type": "number"
              },
              {
                "type": "null"
              }
            ],
            "title": "Intensity Gco2"
          },
          "settlement_period": {
            "title": "Settlement Period",
            "type": "integer"
          },
          "soc_kwh": {
            "title": "Soc Kwh",
            "type": "number"
          },
          "solar_kwh": {
            "title": "Solar Kwh",
            "type": "number"
          }
        },
        "required": [
          "settlement_period",
          "charge_kwh",
          "charge_solar_kwh",
          "solar_kwh",
          "discharge_kwh",
          "soc_kwh",
          "import_p_kwh",
          "export_p_kwh",
          "intensity_gco2"
        ],
        "title": "DispatchBucket",
        "type": "object"
      },
      "GenerationMixItem": {
        "properties": {
          "fuel_type": {
            "title": "Fuel Type",
            "type": "string"
          },
          "generation_mw": {
            "title": "Generation Mw",
            "type": "number"
          },
          "share_pct": {
            "anyOf": [
              {
                "type": "number"
              },
              {
                "type": "null"
              }
            ],
            "title": "Share Pct"
          }
        },
        "required": [
          "fuel_type",
          "generation_mw",
          "share_pct"
        ],
        "title": "GenerationMixItem",
        "type": "object"
      },
      "GenerationPoint": {
        "properties": {
          "fuel_type": {
            "title": "Fuel Type",
            "type": "string"
          },
          "generation_mw": {
            "title": "Generation Mw",
            "type": "number"
          },
          "measured_at": {
            "format": "date-time",
            "title": "Measured At",
            "type": "string"
          },
          "share_pct": {
            "anyOf": [
              {
                "type": "number"
              },
              {
                "type": "null"
              }
            ],
            "title": "Share Pct"
          }
        },
        "required": [
          "measured_at",
          "fuel_type",
          "generation_mw",
          "share_pct"
        ],
        "title": "GenerationPoint",
        "type": "object"
      },
      "HTTPValidationError": {
        "properties": {
          "detail": {
            "items": {
              "$ref": "#/components/schemas/ValidationError"
            },
            "title": "Detail",
            "type": "array"
          }
        },
        "title": "HTTPValidationError",
        "type": "object"
      },
      "IntradayBucket": {
        "description": "Distribution of a metric at a given hour-of-day across the profiled window.",
        "properties": {
          "hour": {
            "title": "Hour",
            "type": "integer"
          },
          "p10": {
            "title": "P10",
            "type": "number"
          },
          "p25": {
            "title": "P25",
            "type": "number"
          },
          "p50": {
            "title": "P50",
            "type": "number"
          },
          "p75": {
            "title": "P75",
            "type": "number"
          },
          "p90": {
            "title": "P90",
            "type": "number"
          }
        },
        "required": [
          "hour",
          "p10",
          "p25",
          "p50",
          "p75",
          "p90"
        ],
        "title": "IntradayBucket",
        "type": "object"
      },
      "MetricProfile": {
        "description": "How a metric typically behaves \u2014 across the day (bands) and the week (heatmap).",
        "properties": {
          "days": {
            "title": "Days",
            "type": "integer"
          },
          "intraday": {
            "items": {
              "$ref": "#/components/schemas/IntradayBucket"
            },
            "title": "Intraday",
            "type": "array"
          },
          "metric": {
            "title": "Metric",
            "type": "string"
          },
          "weekly": {
            "items": {
              "$ref": "#/components/schemas/WeekdayHourCell"
            },
            "title": "Weekly",
            "type": "array"
          }
        },
        "required": [
          "metric",
          "days",
          "intraday",
          "weekly"
        ],
        "title": "MetricProfile",
        "type": "object"
      },
      "MonthlySaving": {
        "properties": {
          "carbon_saved_kg": {
            "title": "Carbon Saved Kg",
            "type": "number"
          },
          "month": {
            "format": "date",
            "title": "Month",
            "type": "string"
          },
          "saving_gbp": {
            "title": "Saving Gbp",
            "type": "number"
          }
        },
        "required": [
          "month",
          "saving_gbp",
          "carbon_saved_kg"
        ],
        "title": "MonthlySaving",
        "type": "object"
      },
      "Price": {
        "properties": {
          "apx_price": {
            "anyOf": [
              {
                "type": "number"
              },
              {
                "type": "null"
              }
            ],
            "title": "Apx Price"
          },
          "n2ex_price": {
            "anyOf": [
              {
                "type": "number"
              },
              {
                "type": "null"
              }
            ],
            "title": "N2Ex Price"
          },
          "net_imbalance_volume": {
            "title": "Net Imbalance Volume",
            "type": "number"
          },
          "settlement_period": {
            "title": "Settlement Period",
            "type": "integer"
          },
          "system_price": {
            "title": "System Price",
            "type": "number"
          }
        },
        "required": [
          "settlement_period",
          "system_price",
          "net_imbalance_volume",
          "apx_price",
          "n2ex_price"
        ],
        "title": "Price",
        "type": "object"
      },
      "PriceCarbonBucket": {
        "description": "Import-price distribution + typical export/carbon for one settlement period.",
        "properties": {
          "carbon_p50": {
            "anyOf": [
              {
                "type": "number"
              },
              {
                "type": "null"
              }
            ],
            "title": "Carbon P50"
          },
          "export_p50": {
            "title": "Export P50",
            "type": "number"
          },
          "import_p10": {
            "title": "Import P10",
            "type": "number"
          },
          "import_p25": {
            "title": "Import P25",
            "type": "number"
          },
          "import_p50": {
            "title": "Import P50",
            "type": "number"
          },
          "import_p75": {
            "title": "Import P75",
            "type": "number"
          },
          "import_p90": {
            "title": "Import P90",
            "type": "number"
          },
          "settlement_period": {
            "title": "Settlement Period",
            "type": "integer"
          },
          "solar_cf_p50": {
            "anyOf": [
              {
                "type": "number"
              },
              {
                "type": "null"
              }
            ],
            "title": "Solar Cf P50"
          }
        },
        "required": [
          "settlement_period",
          "import_p10",
          "import_p25",
          "import_p50",
          "import_p75",
          "import_p90",
          "export_p50",
          "carbon_p50",
          "solar_cf_p50"
        ],
        "title": "PriceCarbonBucket",
        "type": "object"
      },
      "PricePoint": {
        "properties": {
          "apx_price": {
            "anyOf": [
              {
                "type": "number"
              },
              {
                "type": "null"
              }
            ],
            "title": "Apx Price"
          },
          "n2ex_price": {
            "anyOf": [
              {
                "type": "number"
              },
              {
                "type": "null"
              }
            ],
            "title": "N2Ex Price"
          },
          "net_imbalance_volume": {
            "title": "Net Imbalance Volume",
            "type": "number"
          },
          "period_start": {
            "format": "date-time",
            "title": "Period Start",
            "type": "string"
          },
          "settlement_period": {
            "title": "Settlement Period",
            "type": "integer"
          },
          "system_price": {
            "title": "System Price",
            "type": "number"
          }
        },
        "required": [
          "period_start",
          "settlement_period",
          "system_price",
          "net_imbalance_volume",
          "apx_price",
          "n2ex_price"
        ],
        "title": "PricePoint",
        "type": "object"
      },
      "Snapshot": {
        "description": "Latest values across all domains for the dashboard's first paint.",
        "properties": {
          "carbon": {
            "anyOf": [
              {
                "$ref": "#/components/schemas/Carbon"
              },
              {
                "type": "null"
              }
            ]
          },
          "frequency_hz": {
            "anyOf": [
              {
                "type": "number"
              },
              {
                "type": "null"
              }
            ],
            "title": "Frequency Hz"
          },
          "generation": {
            "items": {
              "$ref": "#/components/schemas/GenerationMixItem"
            },
            "title": "Generation",
            "type": "array"
          },
          "measured_at": {
            "anyOf": [
              {
                "format": "date-time",
                "type": "string"
              },
              {
                "type": "null"
              }
            ],
            "title": "Measured At"
          },
          "price": {
            "anyOf": [
              {
                "$ref": "#/components/schemas/Price"
              },
              {
                "type": "null"
              }
            ]
          },
          "supply_demand": {
            "anyOf": [
              {
                "$ref": "#/components/schemas/SupplyDemand"
              },
              {
                "type": "null"
              }
            ]
          }
        },
        "required": [
          "measured_at",
          "generation",
          "supply_demand",
          "carbon",
          "price",
          "frequency_hz"
        ],
        "title": "Snapshot",
        "type": "object"
      },
      "StrategyRun": {
        "description": "One simulated (strategy \u00d7 optimizer) run over the window.",
        "properties": {
          "carbon_saved_kg_year": {
            "title": "Carbon Saved Kg Year",
            "type": "number"
          },
          "cycles": {
            "title": "Cycles",
            "type": "number"
          },
          "monthly": {
            "items": {
              "$ref": "#/components/schemas/MonthlySaving"
            },
            "title": "Monthly",
            "type": "array"
          },
          "optimizer": {
            "title": "Optimizer",
            "type": "string"
          },
          "payback_years": {
            "anyOf": [
              {
                "type": "number"
              },
              {
                "type": "null"
              }
            ],
            "title": "Payback Years"
          },
          "saving_gbp": {
            "title": "Saving Gbp",
            "type": "number"
          },
          "saving_gbp_year": {
            "title": "Saving Gbp Year",
            "type": "number"
          },
          "strategy": {
            "title": "Strategy",
            "type": "string"
          },
          "typical_day": {
            "items": {
              "$ref": "#/components/schemas/DispatchBucket"
            },
            "title": "Typical Day",
            "type": "array"
          }
        },
        "required": [
          "strategy",
          "optimizer",
          "saving_gbp",
          "saving_gbp_year",
          "carbon_saved_kg_year",
          "cycles",
          "payback_years",
          "typical_day",
          "monthly"
        ],
        "title": "StrategyRun",
        "type": "object"
      },
      "SupplyDemand": {
        "properties": {
          "demand_mw": {
            "title": "Demand Mw",
            "type": "integer"
          },
          "settlement_period": {
            "title": "Settlement Period",
            "type": "integer"
          },
          "total_generation_mw": {
            "anyOf": [
              {
                "type": "number"
              },
              {
                "type": "null"
              }
            ],
            "title": "Total Generation Mw"
          },
          "transmission_demand_mw": {
            "title": "Transmission Demand Mw",
            "type": "integer"
          }
        },
        "required": [
          "settlement_period",
          "demand_mw",
          "transmission_demand_mw",
          "total_generation_mw"
        ],
        "title": "SupplyDemand",
        "type": "object"
      },
      "SupplyDemandPoint": {
        "properties": {
          "demand_mw": {
            "title": "Demand Mw",
            "type": "integer"
          },
          "period_start": {
            "format": "date-time",
            "title": "Period Start",
            "type": "string"
          },
          "settlement_period": {
            "title": "Settlement Period",
            "type": "integer"
          },
          "total_generation_mw": {
            "anyOf": [
              {
                "type": "number"
              },
              {
                "type": "null"
              }
            ],
            "title": "Total Generation Mw"
          },
          "transmission_demand_mw": {
            "title": "Transmission Demand Mw",
            "type": "integer"
          }
        },
        "required": [
          "period_start",
          "settlement_period",
          "demand_mw",
          "transmission_demand_mw",
          "total_generation_mw"
        ],
        "title": "SupplyDemandPoint",
        "type": "object"
      },
      "TimeseriesPoint": {
        "properties": {
          "bucket": {
            "format": "date-time",
            "title": "Bucket",
            "type": "string"
          },
          "value": {
            "title": "Value",
            "type": "number"
          }
        },
        "required": [
          "bucket",
          "value"
        ],
        "title": "TimeseriesPoint",
        "type": "object"
      },
      "ValidationError": {
        "properties": {
          "ctx": {
            "title": "Context",
            "type": "object"
          },
          "input": {
            "title": "Input"
          },
          "loc": {
            "items": {
              "anyOf": [
                {
                  "type": "string"
                },
                {
                  "type": "integer"
                }
              ]
            },
            "title": "Location",
            "type": "array"
          },
          "msg": {
            "title": "Message",
            "type": "string"
          },
          "type": {
            "title": "Error Type",
            "type": "string"
          }
        },
        "required": [
          "loc",
          "msg",
          "type"
        ],
        "title": "ValidationError",
        "type": "object"
      },
      "WeekdayHourCell": {
        "properties": {
          "hour": {
            "title": "Hour",
            "type": "integer"
          },
          "median": {
            "title": "Median",
            "type": "number"
          },
          "weekday": {
            "title": "Weekday",
            "type": "integer"
          }
        },
        "required": [
          "weekday",
          "hour",
          "median"
        ],
        "title": "WeekdayHourCell",
        "type": "object"
      }
    }
  },
  "info": {
    "title": "TianguisWatt API",
    "version": "0.1.0"
  },
  "openapi": "3.1.0",
  "paths": {
    "/api/accepted-actions": {
      "get": {
        "operationId": "accepted_actions_api_accepted_actions_get",
        "parameters": [
          {
            "description": "Number of recent actions.",
            "in": "query",
            "name": "limit",
            "required": false,
            "schema": {
              "default": 8,
              "description": "Number of recent actions.",
              "maximum": 50,
              "minimum": 1,
              "title": "Limit",
              "type": "integer"
            }
          }
        ],
        "responses": {
          "200": {
            "content": {
              "application/json": {
                "schema": {
                  "items": {
                    "$ref": "#/components/schemas/AcceptedAction"
                  },
                  "title": "Response Accepted Actions Api Accepted Actions Get",
                  "type": "array"
                }
              }
            },
            "description": "Successful Response"
          },
          "422": {
            "content": {
              "application/json": {
                "schema": {
                  "$ref": "#/components/schemas/HTTPValidationError"
                }
              }
            },
            "description": "Validation Error"
          }
        },
        "summary": "Accepted Actions"
      }
    },
    "/api/battery/context": {
      "get": {
        "operationId": "battery_context_api_battery_context_get",
        "parameters": [
          {
            "description": "Months of history to simulate.",
            "in": "query",
            "name": "months",
            "required": false,
            "schema": {
              "default": 12,
              "description": "Months of history to simulate.",
              "maximum": 24,
              "minimum": 1,
              "title": "Months",
              "type": "integer"
            }
          }
        ],
        "responses": {
          "200": {
            "content": {
              "application/json": {
                "schema": {
                  "$ref": "#/components/schemas/BatteryContext"
                }
              }
            },
            "description": "Successful Response"
          },
          "422": {
            "content": {
              "application/json": {
                "schema": {
                  "$ref": "#/components/schemas/HTTPValidationError"
                }
              }
            },
            "description": "Validation Error"
          }
        },
        "summary": "Battery Context"
      }
    },
    "/api/battery/simulation": {
      "get": {
        "operationId": "battery_simulation_api_battery_simulation_get",
        "parameters": [
          {
            "in": "query",
            "name": "battery",
            "required": false,
            "schema": {
              "default": "10kwh",
              "enum": [
                "5kwh",
                "10kwh",
                "13.5kwh"
              ],
              "title": "Battery",
              "type": "string"
            }
          },
          {
            "in": "query",
            "name": "household",
            "required": false,
            "schema": {
              "default": "medium",
              "enum": [
                "low",
                "medium",
                "high",
                "electrified"
              ],
              "title": "Household",
              "type": "string"
            }
          },
          {
            "in": "query",
            "name": "solar",
            "required": false,
            "schema": {
              "default": "none",
              "enum": [
                "none",
                "3.5kwp",
                "5kwp"
              ],
              "title": "Solar",
              "type": "string"
            }
          },
          {
            "description": "Months of history to simulate.",
            "in": "query",
            "name": "months",
            "required": false,
            "schema": {
              "default": 12,
              "description": "Months of history to simulate.",
              "maximum": 24,
              "minimum": 1,
              "title": "Months",
              "type": "integer"
            }
          }
        ],
        "responses": {
          "200": {
            "content": {
              "application/json": {
                "schema": {
                  "$ref": "#/components/schemas/BatterySimulation"
                }
              }
            },
            "description": "Successful Response"
          },
          "422": {
            "content": {
              "application/json": {
                "schema": {
                  "$ref": "#/components/schemas/HTTPValidationError"
                }
              }
            },
            "description": "Validation Error"
          }
        },
        "summary": "Battery Simulation"
      }
    },
    "/api/bid-stack": {
      "get": {
        "operationId": "bid_stack_api_bid_stack_get",
        "responses": {
          "200": {
            "content": {
              "application/json": {
                "schema": {
                  "$ref": "#/components/schemas/BidStack"
                }
              }
            },
            "description": "Successful Response"
          }
        },
        "summary": "Bid Stack"
      }
    },
    "/api/carbon": {
      "get": {
        "operationId": "carbon_api_carbon_get",
        "parameters": [
          {
            "description": "History window in hours.",
            "in": "query",
            "name": "hours",
            "required": false,
            "schema": {
              "default": 6,
              "description": "History window in hours.",
              "maximum": 168,
              "minimum": 1,
              "title": "Hours",
              "type": "integer"
            }
          }
        ],
        "responses": {
          "200": {
            "content": {
              "application/json": {
                "schema": {
                  "items": {
                    "$ref": "#/components/schemas/CarbonPoint"
                  },
                  "title": "Response Carbon Api Carbon Get",
                  "type": "array"
                }
              }
            },
            "description": "Successful Response"
          },
          "422": {
            "content": {
              "application/json": {
                "schema": {
                  "$ref": "#/components/schemas/HTTPValidationError"
                }
              }
            },
            "description": "Validation Error"
          }
        },
        "summary": "Carbon"
      }
    },
    "/api/events": {
      "get": {
        "description": "Stream update events; the client refetches the affected endpoints on each.",
        "operationId": "events_api_events_get",
        "responses": {
          "200": {
            "content": {
              "application/json": {
                "schema": {}
              }
            },
            "description": "Successful Response"
          }
        },
        "summary": "Events"
      }
    },
    "/api/generation": {
      "get": {
        "operationId": "generation_api_generation_get",
        "parameters": [
          {
            "description": "History window in hours.",
            "in": "query",
            "name": "hours",
            "required": false,
            "schema": {
              "default": 6,
              "description": "History window in hours.",
              "maximum": 168,
              "minimum": 1,
              "title": "Hours",
              "type": "integer"
            }
          }
        ],
        "responses": {
          "200": {
            "content": {
              "application/json": {
                "schema": {
                  "items": {
                    "$ref": "#/components/schemas/GenerationPoint"
                  },
                  "title": "Response Generation Api Generation Get",
                  "type": "array"
                }
              }
            },
            "description": "Successful Response"
          },
          "422": {
            "content": {
              "application/json": {
                "schema": {
                  "$ref": "#/components/schemas/HTTPValidationError"
                }
              }
            },
            "description": "Validation Error"
          }
        },
        "summary": "Generation"
      }
    },
    "/api/health": {
      "get": {
        "description": "Liveness probe.",
        "operationId": "health_api_health_get",
        "responses": {
          "200": {
            "content": {
              "application/json": {
                "schema": {
                  "additionalProperties": {
                    "type": "string"
                  },
                  "title": "Response Health Api Health Get",
                  "type": "object"
                }
              }
            },
            "description": "Successful Response"
          }
        },
        "summary": "Health"
      }
    },
    "/api/prices": {
      "get": {
        "operationId": "prices_api_prices_get",
        "parameters": [
          {
            "description": "History window in hours.",
            "in": "query",
            "name": "hours",
            "required": false,
            "schema": {
              "default": 6,
              "description": "History window in hours.",
              "maximum": 168,
              "minimum": 1,
              "title": "Hours",
              "type": "integer"
            }
          }
        ],
        "responses": {
          "200": {
            "content": {
              "application/json": {
                "schema": {
                  "items": {
                    "$ref": "#/components/schemas/PricePoint"
                  },
                  "title": "Response Prices Api Prices Get",
                  "type": "array"
                }
              }
            },
            "description": "Successful Response"
          },
          "422": {
            "content": {
              "application/json": {
                "schema": {
                  "$ref": "#/components/schemas/HTTPValidationError"
                }
              }
            },
            "description": "Validation Error"
          }
        },
        "summary": "Prices"
      }
    },
    "/api/profile": {
      "get": {
        "operationId": "profile_api_profile_get",
        "parameters": [
          {
            "in": "query",
            "name": "metric",
            "required": true,
            "schema": {
              "enum": [
                "demand",
                "generation",
                "carbon",
                "price"
              ],
              "title": "Metric",
              "type": "string"
            }
          },
          {
            "description": "Days of history to profile.",
            "in": "query",
            "name": "days",
            "required": false,
            "schema": {
              "default": 30,
              "description": "Days of history to profile.",
              "maximum": 365,
              "minimum": 1,
              "title": "Days",
              "type": "integer"
            }
          }
        ],
        "responses": {
          "200": {
            "content": {
              "application/json": {
                "schema": {
                  "$ref": "#/components/schemas/MetricProfile"
                }
              }
            },
            "description": "Successful Response"
          },
          "422": {
            "content": {
              "application/json": {
                "schema": {
                  "$ref": "#/components/schemas/HTTPValidationError"
                }
              }
            },
            "description": "Validation Error"
          }
        },
        "summary": "Profile"
      }
    },
    "/api/snapshot": {
      "get": {
        "operationId": "snapshot_api_snapshot_get",
        "responses": {
          "200": {
            "content": {
              "application/json": {
                "schema": {
                  "$ref": "#/components/schemas/Snapshot"
                }
              }
            },
            "description": "Successful Response"
          }
        },
        "summary": "Snapshot"
      }
    },
    "/api/supply-demand": {
      "get": {
        "operationId": "supply_demand_api_supply_demand_get",
        "parameters": [
          {
            "description": "History window in hours.",
            "in": "query",
            "name": "hours",
            "required": false,
            "schema": {
              "default": 6,
              "description": "History window in hours.",
              "maximum": 168,
              "minimum": 1,
              "title": "Hours",
              "type": "integer"
            }
          }
        ],
        "responses": {
          "200": {
            "content": {
              "application/json": {
                "schema": {
                  "items": {
                    "$ref": "#/components/schemas/SupplyDemandPoint"
                  },
                  "title": "Response Supply Demand Api Supply Demand Get",
                  "type": "array"
                }
              }
            },
            "description": "Successful Response"
          },
          "422": {
            "content": {
              "application/json": {
                "schema": {
                  "$ref": "#/components/schemas/HTTPValidationError"
                }
              }
            },
            "description": "Validation Error"
          }
        },
        "summary": "Supply Demand"
      }
    },
    "/api/timeseries": {
      "get": {
        "operationId": "timeseries_api_timeseries_get",
        "parameters": [
          {
            "in": "query",
            "name": "metric",
            "required": true,
            "schema": {
              "enum": [
                "demand",
                "generation",
                "carbon",
                "price"
              ],
              "title": "Metric",
              "type": "string"
            }
          },
          {
            "in": "query",
            "name": "granularity",
            "required": false,
            "schema": {
              "default": "hour",
              "enum": [
                "sp",
                "hour",
                "day"
              ],
              "title": "Granularity",
              "type": "string"
            }
          },
          {
            "description": "Window in hours (max 30 days).",
            "in": "query",
            "name": "hours",
            "required": false,
            "schema": {
              "default": 24,
              "description": "Window in hours (max 30 days).",
              "maximum": 720,
              "minimum": 1,
              "title": "Hours",
              "type": "integer"
            }
          }
        ],
        "responses": {
          "200": {
            "content": {
              "application/json": {
                "schema": {
                  "items": {
                    "$ref": "#/components/schemas/TimeseriesPoint"
                  },
                  "title": "Response Timeseries Api Timeseries Get",
                  "type": "array"
                }
              }
            },
            "description": "Successful Response"
          },
          "422": {
            "content": {
              "application/json": {
                "schema": {
                  "$ref": "#/components/schemas/HTTPValidationError"
                }
              }
            },
            "description": "Validation Error"
          }
        },
        "summary": "Timeseries"
      }
    }
  }
}
